Metadata-Version: 2.1
Name: Majhool-Bionomial
Version: 0.1
Summary: Gaussian distributions
